MANIFEST.in
README.rst
setup.py
genmenu/__init__.py
genmenu/genmenu.py
genmenu.egg-info/PKG-INFO
genmenu.egg-info/SOURCES.txt
genmenu.egg-info/dependency_links.txt
genmenu.egg-info/not-zip-safe
genmenu.egg-info/top_level.txt