Metadata-Version: 1.0
Name: genmenu
Version: 0.1.8
Summary: A meal menu planner
Home-page: https://github.com/peerster/genmenu
Author: Pär Berge
Author-email: paer.berge@gmail.com
License: MIT
Platform: UNKNOWN
